Xclient/__init__.py
Xclient/asyncio_utils.py
Xclient/client.py
Xclient/constants.py
Xclient/embeddings.py
Xclient/exceptions.py
Xclient/llms.py
Xclient/reranking.py
Xclient/utils.py
Xclient/version.py
Xclient/warnings.py
Xclient/model_config/__init__.py
Xclient/model_config/common.py
Xclient/model_config/generator.py
Xclient/model_config/model_config.py
Xclient/model_config/parser.py
Xclient/model_config/tensor.py
Xclient/model_config/triton_model_config.py
Xclient/tests/__init__.py
Xclient/tests/test_chatmetalm.py
Xclient/tests/test_connect.py
Xclient/tests/test_embeddings.py
Xclient/tests/test_model_call.py
Xclient/tests/test_rerank.py
Xclient/tests/test_stop.py
metalm_xclient-0.1.0.dist-info/LICENSE
metalm_xclient-0.1.0.dist-info/METADATA
metalm_xclient-0.1.0.dist-info/WHEEL
metalm_xclient-0.1.0.dist-info/top_level.txt
metalm_xclient-0.1.0.dist-info/RECORD
